Metadata-Version: 1.0
Name: distributions-classs
Version: 1.2
Summary: Gaussian and binomial distributions
Home-page: UNKNOWN
Author: Femi Adejumo
Author-email: sanyafemi21@gmail.com
License: UNKNOWN
Platform: UNKNOWN
